CHANGES.txt
MANIFEST.in
setup.py
franges/__init__.py
franges/drange.py
franges/frange.py
franges.egg-info/PKG-INFO
franges.egg-info/SOURCES.txt
franges.egg-info/dependency_links.txt
franges.egg-info/top_level.txt
tests/__init__.py
tests/test_drange.py
tests/test_frange.py