Metadata-Version: 1.1
Name: franges
Version: 1.0.1
Summary: Franges adds support for floating point and fixed precision (Decimal) range generator functions.
Home-page: https://github.com/nisanharamati/franges
Author: Nisan Haramati
Author-email: hanisan@gmail.com
License: LGPLv3+
Platform: UNKNOWN
Classifier: Development Status :: 5 - Production/Stable
Classifier: Topic :: Utilities
Classifier: License :: OSI Approved :: GNU Lesser General Public License v3 or later (LGPLv3+)
Classifier: Programming Language :: Python
Classifier: Programming Language :: Python :: 2
Classifier: Programming Language :: Python :: 2.6
Classifier: Programming Language :: Python :: 2.7
Classifier: Programming Language :: Python :: 3
Classifier: Programming Language :: Python :: 3.3
Classifier: Programming Language :: Python :: 3.4
Classifier: Topic :: Software Development :: Libraries
